dask_ngs/__init__.py
dask_ngs/_index.py
dask_ngs/py.typed
dask_ngs-0.1.0.dist-info/METADATA
dask_ngs-0.1.0.dist-info/WHEEL
dask_ngs-0.1.0.dist-info/licenses/LICENSE
dask_ngs-0.1.0.dist-info/RECORD
